{
    "-tBHZ": {
        "id": "-tBHZ",
        "name": "Roberto BARRRRR",
        "address": {
            "streetAddress": "Jasomirgottstraße",
            "number": "7",
            "city": "Vienna",
            "postalCode": "1010"
        },
        "website": "https://www.robertosbar.at",
        "categories": [
            "cocktail",
            "friends",
            "business",
            "date",
            "between",
            "dddollar"
        ]
    },
    "qtU8Y": {
        "id": "qtU8Y",
        "name": "Truth & Dare ",
        "address": {
            "streetAddress": "Schönlaterngasse",
            "number": "4",
            "city": "Vienna",
            "postalCode": "1010"
        },
        "website": "https://www.truthanddare.bar",
        "categories": [
            "cocktail",
            "friends",
            "date",
            "easygoing",
            "dddollar"
        ]
    },
    "ElXbY": {
        "id": "ElXbY",
        "name": "Oswald & Kalb",
        "address": {
            "streetAddress": "Bäckerstraße ",
            "number": "14",
            "city": "Vienna",
            "postalCode": "1010"
        },
        "website": "https://www.oswaldundkalb.at",
        "categories": [
            "wine",
            "aroundhere",
            "friends",
            "business",
            "date",
            "eat",
            "lunch",
            "dinner",
            "between",
            "ddollar"
        ]
    },
    "vUajJ": {
        "id": "vUajJ",
        "name": "Heunisch & Erben",
        "address": {
            "streetAddress": "Landstraßer Hauptstraße ",
            "number": "17",
            "city": "Vienna",
            "postalCode": "1030"
        },
        "website": "https://www.heunisch.at",
        "categories": [
            "wine",
            "fusion",
            "friends",
            "business",
            "date",
            "eat",
            "lunch",
            "dinner",
            "between",
            "dddollar"
        ]
    },
    "2l7LX": {
        "id": "2l7LX",
        "name": "Umar Fisch Bar",
        "address": {
            "streetAddress": "Naschmarkt Stand",
            "number": "",
            "city": "Vienna",
            "postalCode": "1060"
        },
        "website": "https://www.umarfischbar.at",
        "categories": [
            "friends",
            "business",
            "date",
            "lunch",
            "dinner",
            "between",
            "ddollar",
            "fromthesea",
            "fusion",
            "wine"
        ]
    },
    "-gAeo": {
        "id": "-gAeo",
        "name": "Kornat",
        "address": {
            "streetAddress": "Marc-Aurel-Straße",
            "number": "8",
            "city": "Vienna",
            "postalCode": "1010"
        },
        "website": "https://www.kornat.at",
        "categories": [
            "fromthesea",
            "friends",
            "business",
            "date",
            "eat",
            "lunch",
            "dinner",
            "between",
            "ddollar"
        ]
    },
    "hlXPc": {
        "id": "hlXPc",
        "name": "XO Grill",
        "address": {
            "streetAddress": "Gumpendorfer Straße",
            "number": "",
            "city": "Vienna",
            "postalCode": "1060"
        },
        "website": "https://www.xo-grill.at",
        "categories": [
            "friends",
            "lunch",
            "dinner",
            "latesnack",
            "easygoing",
            "ddollar",
            "fireland",
            "streetfood"
        ]
    },
    "Y9qd3": {
        "id": "Y9qd3",
        "name": "ignacio vinos e ibéricos",
        "address": {
            "streetAddress": "Salztorgasse ",
            "number": "7",
            "city": "Vienna",
            "postalCode": "1010"
        },
        "website": "https://www.ignacio.at",
        "categories": [
            "bites",
            "wine",
            "friends",
            "business",
            "date",
            "eat",
            "lunch",
            "dinner",
            "latesnack",
            "easygoing",
            "ddollar"
        ]
    },
    "bOPV8": {
        "id": "bOPV8",
        "name": "BEAULIEU Épicerie fine & Bistrot",
        "address": {
            "streetAddress": "Herrengasse",
            "number": "14",
            "city": "Vienna",
            "postalCode": "1010"
        },
        "website": "https://www.beaulieu-wien.at",
        "categories": [
            "bistrofrancais",
            "friends",
            "business",
            "date",
            "eat",
            "breakfast",
            "brunch",
            "lunch",
            "dinner",
            "between",
            "ddollar"
        ]
    },
    "NSWuO": {
        "id": "NSWuO",
        "name": "IKI Restaurant",
        "address": {
            "streetAddress": "Am Belvedere",
            "number": "1",
            "city": "Vienna",
            "postalCode": "1100"
        },
        "website": "https://www.iki-restaurant.at",
        "categories": [
            "farawayasia",
            "friends",
            "business",
            "date",
            "family",
            "eat",
            "lunch",
            "dinner",
            "easygoing",
            "ddollar"
        ]
    },
    "HRPJ3": {
        "id": "HRPJ3",
        "name": "Elissar",
        "address": {
            "streetAddress": "Johannesgasse ",
            "number": "27",
            "city": "Vienna",
            "postalCode": "1010"
        },
        "website": "https://www.elissar.at",
        "categories": [
            "hummus",
            "friends",
            "business",
            "date",
            "family",
            "eat",
            "lunch",
            "dinner",
            "between",
            "ddollar"
        ]
    },
    "gcF_J": {
        "id": "gcF_J",
        "name": "Seven North",
        "address": {
            "streetAddress": "Schottenfeldgasse ",
            "number": "74",
            "city": "Vienna",
            "postalCode": "1070"
        },
        "website": "https://www.sevennorthrestaurant.at",
        "categories": [
            "friends",
            "business",
            "date",
            "family",
            "dinner",
            "latesnack",
            "between",
            "ddollar",
            "hummus",
            "fusion",
            "cocktail"
        ]
    },
    "UmkU0": {
        "id": "UmkU0",
        "name": "Okra Izakaya",
        "address": {
            "streetAddress": "Kleine Pfarrgasse ",
            "number": "1",
            "city": "Vienna",
            "postalCode": "1020"
        },
        "website": "https://www.okra1020.com",
        "categories": [
            "farawayasia",
            "friends",
            "business",
            "date",
            "family",
            "eat",
            "dinner",
            "between",
            "ddollar"
        ]
    },
    "4536V": {
        "id": "4536V",
        "name": "Shokudo Kuishimbo",
        "address": {
            "streetAddress": "Esterhazygasse ",
            "number": "12",
            "city": "Vienna",
            "postalCode": "1060"
        },
        "website": "https://www.shokudokuishimbo.com",
        "categories": [
            "farawayasia",
            "friends",
            "date",
            "family",
            "eat",
            "lunch",
            "dinner",
            "easygoing",
            "ddollar"
        ]
    },
    "SQrKO": {
        "id": "SQrKO",
        "name": "Mochi",
        "address": {
            "streetAddress": "Praterstraße",
            "number": "15",
            "city": "Vienna",
            "postalCode": "1020"
        },
        "website": "https://www.mochi.at",
        "categories": [
            "farawayasia",
            "friends",
            "business",
            "date",
            "eat",
            "lunch",
            "dinner",
            "easygoing",
            "ddollar"
        ]
    },
    "mCStJ": {
        "id": "mCStJ",
        "name": "MAST Weinbistro",
        "address": {
            "streetAddress": "Porzellangasse ",
            "number": "53",
            "city": "Vienna",
            "postalCode": "1090"
        },
        "website": "https://www.mast.wine",
        "categories": [
            "friends",
            "date",
            "lunch",
            "dinner",
            "between",
            "dddollar",
            "aroundhere",
            "fusion",
            "wine"
        ]
    },
    "401-m": {
        "id": "401-m",
        "name": "Grace",
        "address": {
            "streetAddress": "Danhausergasse ",
            "number": "3",
            "city": "Vienna",
            "postalCode": "1040"
        },
        "website": "https://www.grace-restaurant.at",
        "categories": [
            "friends",
            "business",
            "date",
            "family",
            "dinner",
            "between",
            "dddollar",
            "fusion",
            "wine"
        ]
    },
    "4Dfli": {
        "id": "4Dfli",
        "name": "asdfgh",
        "address": {
            "streetAddress": "aaaastreeet",
            "number": "12",
            "city": "Vienna",
            "postalCode": "1212"
        },
        "website": "https://www.at.at",
        "categories": [
            "family",
            "patisserie",
            "easygoing",
            "ddollar",
            "hummus",
            "wine"
        ]
    }
}